vsi2tif/__init__.py
vsi2tif/vsi2tif.py
vsi2tif/src/__init__.py
vsi2tif/src/benchmark.py
vsi2tif/src/convert.py
vsi2tif/src/process.py
vsi2tif/src/utils.py
vsi2tif-0.1.6.dist-info/LICENSE
vsi2tif-0.1.6.dist-info/METADATA
vsi2tif-0.1.6.dist-info/WHEEL
vsi2tif-0.1.6.dist-info/entry_points.txt
vsi2tif-0.1.6.dist-info/top_level.txt
vsi2tif-0.1.6.dist-info/RECORD
