Metadata-Version: 2.2
Name: vsi2tif
Version: 0.1.6
Summary: A package for converting images from cellSens VSI format to tiled, pyramidal TIFF
Home-page: https://github.com/andreped/vsi2tif
Author: André Pedersen, Sebastian Krossa, Erik Smistad, David Bouget
Author-email: andrped94@gmail.com
License: MIT
Classifier: Programming Language :: Python :: 3.6
Classifier: Programming Language :: Python :: 3.7
Classifier: Programming Language :: Python :: 3.8
Classifier: Programming Language :: Python :: 3.9
Classifier: Programming Language :: Python :: 3.10
Classifier: Programming Language :: Python :: 3.11
Classifier: Programming Language :: Python :: 3.12
Classifier: License :: OSI Approved :: MIT License
Classifier: Operating System :: OS Independent
Requires-Python: >=3.6
License-File: LICENSE
Requires-Dist: tqdm
Requires-Dist: numpy
Provides-Extra: dev
Requires-Dist: wheel; extra == "dev"
Requires-Dist: setuptools; extra == "dev"
Requires-Dist: black==22.3.0; extra == "dev"
Requires-Dist: isort==5.10.1; extra == "dev"
Requires-Dist: flake8==4.0.1; extra == "dev"
Dynamic: author
Dynamic: author-email
Dynamic: classifier
Dynamic: description
Dynamic: description-content-type
Dynamic: home-page
Dynamic: license
Dynamic: provides-extra
Dynamic: requires-dist
Dynamic: requires-python
Dynamic: summary
